README.md
setup.py
pullrequester/__init__.py
pullrequester/__main__.py
pullrequester/pullrequester.py
pullrequester.egg-info/PKG-INFO
pullrequester.egg-info/SOURCES.txt
pullrequester.egg-info/dependency_links.txt
pullrequester.egg-info/not-zip-safe
pullrequester.egg-info/requires.txt
pullrequester.egg-info/top_level.txt
test/test_pullrequester.py