Metadata-Version: 1.0
Name: pullrequester
Version: 0.1.9
Summary: You use this to create pull requests. And be happier!
Home-page: http://github.com/enkelbr/pullrequester
Author: Gustavo Maia
Author-email: gurumaia@gmail.com
License: GPL
Platform: UNKNOWN
